gcbmwalltowall/__init__.py
gcbmwalltowall/application/__init__.py
gcbmwalltowall/application/walltowall.py
gcbmwalltowall/builder/__init__.py
gcbmwalltowall/builder/casfriprojectbuilder.py
gcbmwalltowall/builder/compositeprojectbuilder.py
gcbmwalltowall/builder/projectbuilder.py
gcbmwalltowall/component/__init__.py
gcbmwalltowall/component/attributetable.py
gcbmwalltowall/component/boundingbox.py
gcbmwalltowall/component/classifier.py
gcbmwalltowall/component/cohort.py
gcbmwalltowall/component/disturbance.py
gcbmwalltowall/component/inputdatabase.py
gcbmwalltowall/component/layer.py
gcbmwalltowall/component/preparedproject.py
gcbmwalltowall/component/project.py
gcbmwalltowall/component/rasterattributetable.py
gcbmwalltowall/component/rollback.py
gcbmwalltowall/component/tileable.py
gcbmwalltowall/component/vectorattributetable.py
gcbmwalltowall/configuration/__init__.py
gcbmwalltowall/configuration/configuration.py
gcbmwalltowall/configuration/gcbmconfigurer.py
gcbmwalltowall/converter/__init__.py
gcbmwalltowall/converter/layerconverter.py
gcbmwalltowall/converter/projectconverter.py
gcbmwalltowall/converter/disturbance/__init__.py
gcbmwalltowall/converter/disturbance/compositedisturbancetypemanager.py
gcbmwalltowall/converter/disturbance/eventmerger.py
gcbmwalltowall/converter/disturbance/mergingdisturbancelayerconverter.py
gcbmwalltowall/converter/disturbance/mergingtransitionconverter.py
gcbmwalltowall/project/__init__.py
gcbmwalltowall/project/projectfactory.py
gcbmwalltowall/runner/__init__.py
gcbmwalltowall/runner/cbm4.py
gcbmwalltowall/util/__init__.py
gcbmwalltowall/util/gdalhelpers.py
gcbmwalltowall/util/numba.py
gcbmwalltowall/util/rasterbound.py
gcbmwalltowall/util/rasterchunks.py
gcbmwalltowall/validation/__init__.py
gcbmwalltowall/validation/generic.py
gcbmwalltowall/validation/string.py
gcbmwalltowall-2.0.3.data/data/Tools/gcbmwalltowall/settings.json
gcbmwalltowall-2.0.3.data/data/Tools/gcbmwalltowall/templates/default/gcbm_config.cfg
gcbmwalltowall-2.0.3.dist-info/METADATA
gcbmwalltowall-2.0.3.dist-info/WHEEL
gcbmwalltowall-2.0.3.dist-info/entry_points.txt
gcbmwalltowall-2.0.3.dist-info/top_level.txt
gcbmwalltowall-2.0.3.dist-info/RECORD
