Metadata-Version: 2.4
Name: gcbmwalltowall
Version: 2.0.3
Summary: gcbmwalltowall
Classifier: Programming Language :: Python :: 3
Requires-Python: >=3.7
Requires-Dist: mojadata>=4.0.3
Requires-Dist: sqlalchemy
Requires-Dist: sqlalchemy-access
Requires-Dist: pandas
Requires-Dist: openpyxl
Requires-Dist: spatial_inventory_rollback>=1.1.0
Dynamic: classifier
Dynamic: requires-dist
Dynamic: requires-python
Dynamic: summary
